{
  "zaton": "Zaton",
  "zat_b44_stalker_barge_name": "Barge",
  "zat_b100_army_2": "Capitano Furtez",
  "zat_b28_draper_name": "Ten Drapei",
  "zat_b28_umerov_name": "Sott. Umerov",
  "zat_b100_army_1": "Sergente Gazda",
  "zat_b28_smoliak_name": "Tenente Smolyak",
  "zat_b100_army_3": "Serg. Magg. Shveiko",
  "st_zat_b100_name": "Anomalia Foresta d\u0027acciaio",
  "st_zat_b101_name": "Palude",
  "st_zat_b14_name": "Stazione di drenaggio",
  "st_zat_b20_name": "Fattoria bruciata",
  "st_zat_b39_name": "Anomalia Pinquercia",
  "st_zat_b53_name": "Anomalia Boiler",
  "st_zat_b54_name": "Anomalia Cicatrice",
  "st_zat_b55_name": "Anomalia Artiglio",
  "zat_a2_stalker_barmen_name": "Beard",
  "zat_b22_stalker_medic_name": "Tremor",
  "st_zat_b30_owl_stalker_trader_name": "Owl",
  "st_zat_a2_stalker_nimble_name": "Nimble",
  "stalker": "Stalker",
  "st_zat_b106_stalker_crab_name": "Crab",
  "st_zat_b106_stalker_garmata_name": "Garmata",
  "st_zat_b106_stalker_gonta_name": "Gonta",
  "zat_b215_stalker_guide_name": "Pilot",
  "zat_b33_stalker_snag": "Snag",
  "st_zat_b38_stalker_cop_name": "Grouse",
  "st_zat_b7_bandit_boss_sultan_name": "Sultan",
  "bandit": "Bandito",
  "st_zat_a2_name": "Skadovsk",
  "st_zat_b103_name": "Officine delle sotto-stazioni",
  "st_zat_b104_name": "Segheria",
  "st_zat_b106_name": "Izumrudnoye",
  "st_zat_b12_name": "Ponte di Preobrazhensky",
  "st_zat_b18_name": "Vecchia chiatta",
  "st_zat_b28_name": "Altopiano meridionale",
  "st_zat_b33_name": "Stazione di rifornimento",
  "st_zat_b38_name": "Complesso dell\u0027antenna Krug",
  "st_zat_b40_name": "Impianto dei rifiuti",
  "st_zat_b52_name": "Gru del porto",
  "st_zat_b56_name": "Anomalia Circo",
  "st_zat_b5_name": "Stazione dei ranger",
  "st_zat_b7_name": "Shevchenko",
  "zat_b18_noah_name": "Noah",
  "jupiter": "Area circostante Jupiter",
  "jup_b9_shliachin_name": "Serg Shlyachin",
  "st_jup_b1_name": "Anomalia Cumulo di cenere",
  "st_jup_b200_name": "Fabbrica di cemento",
  "st_jup_b201_name": "Anomalia Bagno di cemento",
  "st_jup_b206_name": "Boschetto anomalo",
  "st_jup_b209_name": "Anomalia Bitume",
  "st_jup_b211_name": "Anomalia Plavni",
  "st_jup_b25_name": "Cava",
  "st_jup_b32_name": "Parcheggio",
  "jup_a10_bandit_leader_name": "Jack",
  "st_jup_a12_stalker_assaulter": "Grizzly",
  "st_jup_a12_stalker_diplomat": "Torba",
  "jup_a6_duty_leader": "Ten Col Shulga",
  "dolg": "Duty",
  "jup_a6_freedom_leader": "Loki",
  "freedom": "Freedom",
  "jup_a6_stalker_barmen": "Hawaiano",
  "jup_b10_stalker_drunk": "Senka",
  "st_jup_b43_stalker_assistant": "Garry",
  "jup_a6_stalker_medik": "Conciaossa",
  "jup_b220_trapper": "Trapper",
  "jup_a10_stalker_vano": "Vano",
  "jup_b19_freedom_yar_name": "Zio Yar",
  "jup_b15_zulus": "Zulu",
  "jup_b25_freedom_flint": "Flint",
  "st_jup_a10_name": "Checkpoint",
  "st_jup_a12_name": "Magazzino dei contenitori",
  "st_jup_a6_name": "Yanov",
  "st_jup_a9_name": "Stabilimento Jupiter",
  "st_jup_b19_name": "Kopachy",
  "st_jup_b202_name": "Sotto-stazione",
  "st_jup_b205_name": "Complesso Volkhov AA",
  "st_jup_b208_name": "Tunnel orientale",
  "st_jup_b212_name": "Complesso di ventilazione",
  "st_jup_b46_name": "Torre di raffreddamento",
  "st_jup_b6_name": "Bunker degli scienziati",
  "st_jup_b9_name": "Piattaforme di atterraggio degli elicotteri",
  "jup_b6_scientist_nuclear_physicist": "Professor Hermann",
  "jup_b6_scientist_biochemist": "Professor Ozersky",
  "st_jup_a12_bandit_cashier": "Dwarf",
  "st_jup_a12_bandit_chief": "Shishak",
  "pri_a15_sokolov_name": "Ten Sokolov",
  "jupiter_underground": "Pripyat 1, sottopasso",
  "pripyat": "Pripyat",
  "st_pri_b301_name": "Scuola",
  "st_pri_b302_name": "Anomalia Vite",
  "st_pri_b303_name": "Vecchio centro servizio",
  "st_pri_b304_name": "Grande magazzino",
  "st_pri_b306_name": "Centro servizi Yubileiny",
  "st_pri_b307_name": "Anomalia Vulcano",
  "pri_a18_skorlupko_in_suit_name": "Ten Skelya",
  "army": "Militare",
  "pri_a18_vano_in_suit_reserve_name": "Serg Merkulov",
  "pri_a17_military_sergeant_morozov": "Sergente Morozov",
  "st_pri_a16_name": "Lavanderia",
  "st_pri_a17_name": "Ospedale",
  "st_pri_a18_name": "Libreria",
  "st_pri_a21_name": "Macelleria",
  "st_pri_a25_name": "Asilo",
  "st_pri_a28_name": "Cinema Prometheus",
  "st_pri_b35_name": "Complesso di appartamenti",
  "st_pri_b36_name": "Porto del fiume",
  "pri_a17_military_captain_tarasov": "Capitano Tarasov",
  "labx8": "Laboratorio X8",
  "zat_b44_barge_pda_name": "PDA di Barge",
  "stalker_outfit_name": "Tuta \u0022Alba\u0022",
  "st_wpn_ak74": "AKM-74/2",
  "ammo-5.45x39-fmj": "Munizioni 5.45x39 mm",
  "st_wpn_fort": "Fora-12",
  "ammo-9x18-fmj": "Munizioni 9x18 mm",
  "st_grenade_rgd5": "Granata RGD-5",
  "st_wpn_ak74u": "AKM-74/2U",
  "st_wpn_pm": "PMm",
  "st_af_electra_sparkler_name": "Scintilla",
  "st_af_electra_flash_name": "Lampo",
  "st_af_electra_moonlight_name": "Chiaro di luna",
  "st_af_dummy_battery_name": "Batteria",
  "st_af_dummy_dummy_name": "Conchiglia",
  "st_af_ice_name": "Fiocco di neve",
  "st_af_blood_name": "Sangue di pietra",
  "st_af_mincer_meat_name": "Pezzo di carne",
  "st_af_soul_name": "Anima",
  "st_af_fuzz_kolobok_name": "Kolobok",
  "st_af_baloon_name": "Bolla",
  "st_af_glass_name": "Lucciola",
  "st_af_medusa_name": "Medusa",
  "st_af_cristall_flower_name": "Fiore di pietra",
  "st_af_night_star_name": "Stella della notte",
  "st_af_vyvert_name": "Contorto",
  "st_af_gravi_name": "Gravi",
  "st_af_gold_fish_name": "Pesce rosso",
  "st_af_cristall_name": "Cristallo",
  "st_af_fireball_name": "Ardente",
  "st_af_dummy_glassbeads_name": "Spirale di perle",
  "st_af_eye_name": "Occhio",
  "st_af_fire_name": "Fiamma",
  "st_bread": "Pane",
  "st_kolbasa": "Salsiccia dietetica",
  "st_conserva": "Barattolo \u0022Colazione del turista\u0022",
  "st_vodka": "Vodka \u0022Cosacchi\u0022",
  "st_energy_drink": "Bevanda energetica",
  "st_bandage": "Fasciatura",
  "st_medkit": "Kit di pronto soccorso",
  "st_medkit_science": "Kit di pronto soccorso scientifico",
  "st_medkit_army": "Kit di pronto soccorso militare",
  "st_antirad": "Droghe anti-radiazioni",
  "st_drug_booster": "Ercole",
  "st_drug_coagulant": "Vinca",
  "st_drug_psy_blockade": "Psico-bloccante",
  "st_drug_antidot": "Antidoto",
  "st_drug_radioprotector": "Radioprotettore",
  "st_drug_anabiotic": "Anabiotico",
  "ammo-9x18-pmm": "Munizioni 9x18 mm \u002BP\u002B",
  "ammo-9x19-pbp": "Munizioni 9x19 mm JHP",
  "ammo-9x19-fmj": "Munizioni 9x19 mm FMJ",
  "ammo-11.43x23-hydro": "Munizioni .45 ACP hydro-shock",
  "ammo-11.43x23-fmj": "Munizioni .45 ACP",
  "ammo-12x70-buck": "Munizioni a pallettoni 12x70",
  "ammo-12x76-zhekan": "Munizioni slug 12x76",
  "ammo-5.45x39-ap": "Munizioni 5.45x39 mm AP",
  "ammo-9x39-ap": "Munizioni 9x39 mm SP-6",
  "ammo-9x39-pab9": "Munizioni 9x39 mm SP-5",
  "ammo-5.56x45-ss190": "Munizioni 5.56x45 mm",
  "ammo-5.56x45-ap": "Munizioni 5.56x45 mm AP",
  "ammo-7.62x54-7h14": "Munizioni 7.62x54 mm 7H1",
  "ammo-og-7b": "Testata OG-7V",
  "ammo-vog-25": "Granata VOG-25",
  "st_grenade_f1": "Granata F1",
  "ammo-m209": "Granata M203",
  "ammo-7.62x54-ap_s": "7.62x54 PP",
  "st_wpn_pb": "PB-1s",
  "st_wpn_hpsa": "HPSS-1m",
  "st_wpn_beretta": "Martha",
  "st_wpn_walther": "Walker P9m",
  "st_wpn_sig220": "SIP-t M200",
  "st_wpn_colt1911": "Kora-919",
  "st_wpn_usp": "UDP Compact",
  "st_wpn_eagle": "Aquilone nero",
  "st_wpn_bm16": "Doppietta a canne mozze",
  "st_wpn_toz34": "Doppietta da caccia",
  "st_wpn_wincheaster1300": "Chaser 13",
  "st_wpn_spas12": "SPSA-14 ",
  "st_wpn_mp5": "Viper 5",
  "st_wpn_abakan": "AC-96/2",
  "st_wpn_l85": "IL 86",
  "st_wpn_lr300": "TRs 301",
  "st_wpn_protecta": "Eliminatore",
  "st_wpn_sig550": "SGI-5k",
  "st_wpn_groza": "Tunder S14",
  "st_wpn_val": "SA \u0022Valanga\u0022",
  "st_wpn_vintorez": "Vintar BC ",
  "st_wpn_svu": "SVUmk-2",
  "st_wpn_svd": "SVDm-2",
  "st_wpn_rg6": "Bulldog-6",
  "st_wpn_rpg7": "RPG-7u",
  "st_wpn_g36": "GP37",
  "st_wpn_fn2000": "FT-200M",
  "st_wpn_rp": "RP-74",
  "st_addon_scope": "Mirino PSO-1m",
  "st_addon_scope_x2.7": "Mirino PSU-1",
  "st_addon_scope_detector": "Mirino PSS-2x",
  "st_addon_scope_night_vision": "Mirino NSPU-3",
  "st_addon_scope_susat": "Mirino SUSAT 4x",
  "st_addon_scope_susat_x1.6": "Mirino SUSAT 1.6x",
  "st_addon_scope_susat_custom": "Mirino SUSAT tipo Mera",
  "st_addon_scope_susat_dusk": "Mirino SUSAT x1.6 \u0022Tramonto\u0022",
  "st_addon_scope_susat_night_vision": "Mirino SUSAT x4 \u0022Notte\u0022",
  "st_addon_silencer": "Silenziatore",
  "st_grenade_launcher": "GP-25 Koster",
  "st_grenade_launcher_m203": "M203",
  "novice_outfit_name": "Impermeabile in pelle",
  "specops_outfit_name": "Tuta corazzata Berill-5M",
  "military_outfit_name": "Tuta corazzata Bulat",
  "scientific_outfit_name": "Tuta SEVA",
  "exo_outfit_name": "Esoscheletro",
  "svoboda_light_outfit_name": "Tuta \u0022Vento della Freedom\u0022",
  "svoboda_heavy_outfit_name": "Tuta \u0022Guardia della Freedom\u0022",
  "csky_heavy_outfit_name": "Armatura CS-3a",
  "dolg_outfit_name": "Protezione universale PS5-M",
  "dolg_heavy_outfit_name": "Armatura Duty PSZ-9d",
  "st_helm_respirator": "Maschera antigas",
  "st_helm_hardhat": "Casco d\u0027acciaio",
  "st_helm_protective": "Casco schermato",
  "st_helm_tactic": "Casco tattico",
  "st_helm_battle": "Casco Sphere M12",
  "st_detector1": "Rilevatore \u0022Eco\u0022",
  "st_detector2": "Rilevatore \u0022Orso\u0022",
  "st_detector3": "Rilevatore \u0022Veles\u0022",
  "st_wpn_pm_actor": "PMm onoraria",
  "st_wpn_sig550_strelok": "SGI-5k di Strelok",
  "st_wpn_pkm_zulus": "RP-74 di Zulu",
  "st_wpn_wincheaster1300_trapper": "Predatore",
  "st_wpn_desert_eagle_nimble": "Aquila delle steppe",
  "st_wpn_groza_nimble": "Tempesta",
  "st_wpn_mp5_nimble": "Frasier",
  "st_wpn_sig220_nimble": "Alpina",
  "st_wpn_spas12_nimble": "Fuciliere",
  "st_wpn_svd_nimble": "Lince",
  "st_wpn_svu_nimble": "SVU2-A",
  "st_wpn_usp_nimble": "Marcia",
  "st_wpn_vintorez_nimble": "Marea",
  "st_compass": "Bussola",
  "st_zat_b20_noah_pda_name": "PDA di Noah",
  "st_af_quest_b14_twisted": "Ruota modificata",
  "st_toolkit_1_name": "Attrezzi di base",
  "st_zat_b12_documents_2": "Ordine interno n\u00B0423",
  "st_zat_b40_notebook_name": "Notebook mercenari",
  "zat_b39_joker_pda_name": "PDA di Joker",
  "st_toolkit_2_name": "Attrezzi avanzati",
  "st_zat_a23_gauss_rifle_docs": "Documenti sull\u0027oggetto 62",
  "ammo-gauss": "Batterie",
  "st_detector4": "Rilevatore sperimentale \u0022Svarog\u0022",
  "st_oasis_heart": "Cuore dell\u0027Oasi",
  "jup_a9_conservation_info": "Documenti con annotazioni",
  "jup_a9_delivery_info": "Lettera sulla consegna dell\u0027oggetto 62",
  "jup_a9_evacuation_info": "Cartella con l\u0027ordine",
  "jup_a9_losses_info": "Programma delle consegne",
  "jup_a9_meeting_info": "File notebook",
  "jup_a9_power_info": "Registro del turno",
  "jup_a9_way_info": "Schemi tecnici del sottopasso ",
  "jup_b200_tech_materials_acetone": "Barattolo di colofonia",
  "jup_b200_tech_materials_textolite": "Base di textolite",
  "jup_b200_tech_materials_wire": "Rocchetto di filo di rame",
  "jup_b200_tech_materials_capacitor": "Gruppo di condensatori",
  "jup_b200_tech_materials_transistor": "Scatola di transistor",
  "st_jup_b205_sokolov_note_name": "Messaggio di Sokolov",
  "st_toolkit_3_name": "Attrezzi di precisione",
  "st_pri_a19_lab_x7_info_name": "Ordine di trasferimento",
  "st_pri_a19_lab_x10_info_name": "Emettitore \u0022Arcobaleno\u0022 \u2013 Dati tecnici principali",
  "st_pri_a19_lab_x18_info_name": "Rapporto sullo studio dei campioni",
  "st_pri_a19_american_experiment_info_name": "Notebook con la descrizione di un esperimento",
  "st_lx8_service_instruction_name": "Manuale per l\u0027oggetto 62",
  "st_pri_a19_lab_x16_info_name": "Documenti sulla ricerca",
  "wealthy_functor": "Un ricco cliente",
  "information_dealer_functor": "Trafficante d\u0027informazioni",
  "actor_name": "Maggiore Degtyarev",
  "zat_b30_sultan_loose": "Uno dei nostri",
  "zat_b30_barmen_under_sultan": "Boss",
  "zat_b7_actor_really_helped_bandits": "Il colpo: attacca gli stalker",
  "zat_b7_actor_really_helped_stalkers": "Il colpo: attacca i rapinatori",
  "enemy": "Nemico",
  "neutral": "Neutrale",
  "friend": "Amico",
  "st_name_duty_warehouse_title": "magazzino Duty",
  "st_zaton_b56_name": "Anomalia Circo",
  "research_man_gained": "Assistente ricercatore",
  "pioneer_achievement_gained": "Pioniere",
  "novice": "Principiante",
  "experienced": "Esperto",
  "veteran": "Veterano",
  "master": "Maestro"
}